taskdaemon/__init__.py
taskdaemon-0.1.0.dist-info/METADATA
taskdaemon-0.1.0.dist-info/WHEEL
taskdaemon-0.1.0.dist-info/top_level.txt
taskdaemon-0.1.0.dist-info/RECORD
